datazimmer/__init__.py
datazimmer/aswan_integration.py
datazimmer/config_loading.py
datazimmer/dvc_util.py
datazimmer/exceptions.py
datazimmer/get_runtime.py
datazimmer/gh_actions.py
datazimmer/naming.py
datazimmer/persistent_state.py
datazimmer/pipeline_element.py
datazimmer/project_runtime.py
datazimmer/raw_data.py
datazimmer/registry.py
datazimmer/reporting.py
datazimmer/typer_commands.py
datazimmer/utils.py
datazimmer/validation_functions.py
datazimmer/zenodo.py
datazimmer/metadata/__init__.py
datazimmer/metadata/atoms.py
datazimmer/metadata/complete_id.py
datazimmer/metadata/datascript.py
datazimmer/metadata/high_level.py
datazimmer/metadata/scrutable.py
datazimmer/sql/__init__.py
datazimmer/sql/draw.py
datazimmer/sql/loader.py
datazimmer/tests/__init__.py
datazimmer/tests/create_dogshow.py
datazimmer/tests/test_commands.py
datazimmer/tests/test_config.py
datazimmer/tests/test_full_integration.py
datazimmer/tests/test_registry.py
datazimmer/tests/test_runtime.py
datazimmer/tests/test_scrutable.py
datazimmer/tests/test_sql.py
datazimmer/tests/test_util.py
datazimmer/tests/test_validation.py
datazimmer/tests/util.py
datazimmer-0.5.3.dist-info/entry_points.txt
datazimmer-0.5.3.dist-info/LICENSE
datazimmer-0.5.3.dist-info/WHEEL
datazimmer-0.5.3.dist-info/METADATA
datazimmer-0.5.3.dist-info/RECORD
