Metadata-Version: 2.1
Name: datazimmer
Version: 0.5.3
Summary: sscu-budapest utilities for scientific data engineering
Author-email: Social Science Computing Unit Budapest <borza.endre@krtk.hu>
Requires-Python: >=3.10
Requires-Dist: flit
Requires-Dist: wheel>=0.37.0
Requires-Dist: pip>=22.0.0
Requires-Dist: setuptools>=60.0.0
Requires-Dist: parquetranger>=0.2.3
Requires-Dist: pandas>=2.0.1
Requires-Dist: colassigner>=0.2.2
Requires-Dist: sqlalchemy>=2.0.0
Requires-Dist: pyyaml
Requires-Dist: structlog
Requires-Dist: toml
Requires-Dist: typer
Requires-Dist: cookiecutter
Requires-Dist: sqlmermaid
Requires-Dist: metazimmer
Requires-Dist: zimmauth>=0.1.0
Requires-Dist: aswan[remote]>=0.4.2 ; extra == "collect"
Requires-Dist: branthebuilder[doc] ; extra == "doc"
Requires-Dist: psycopg2 ; extra == "postgres"
Requires-Dist: pyinstrument ; extra == "profile"
Requires-Dist: branthebuilder ; extra == "test"
Requires-Dist: atqo ; extra == "test"
Requires-Dist: faker ; extra == "test"
Requires-Dist: moto ; extra == "test"
Requires-Dist: boto3 ; extra == "test"
Requires-Dist: tabulate ; extra == "test"
Requires-Dist: requests ; extra == "zenodo"
Requires-Dist: markdown2 ; extra == "zenodo"
Project-URL: Homepage, https://github.com/sscu-budapest/datazimmer
Provides-Extra: collect
Provides-Extra: doc
Provides-Extra: postgres
Provides-Extra: profile
Provides-Extra: test
Provides-Extra: zenodo
